hass_frontend/__init__.py
hass_frontend/core.js
hass_frontend/core.js.gz
hass_frontend/frontend.html
hass_frontend/frontend.html.gz
hass_frontend/ha-chart-scripts.html
hass_frontend/ha-chart-scripts.html.gz
hass_frontend/index.html
hass_frontend/index.html.gz
hass_frontend/mdi.html
hass_frontend/mdi.html.gz
hass_frontend/pagedown-js.html
hass_frontend/pagedown-js.html.gz
hass_frontend/robots.txt
hass_frontend/service_worker.js
hass_frontend/service_worker.js.gz
hass_frontend/webcomponents-lite.js
hass_frontend/webcomponents-lite.js.gz
hass_frontend/fonts/roboto/COPYRIGHT.txt
hass_frontend/fonts/roboto/DESCRIPTION.en_us.html
hass_frontend/fonts/roboto/DESCRIPTION.en_us.html.gz
hass_frontend/fonts/roboto/LICENSE.txt
hass_frontend/fonts/roboto/METADATA.json
hass_frontend/fonts/roboto/METADATA.json.gz
hass_frontend/fonts/roboto/Roboto-Black.ttf
hass_frontend/fonts/roboto/Roboto-Black.ttf.gz
hass_frontend/fonts/roboto/Roboto-BlackItalic.ttf
hass_frontend/fonts/roboto/Roboto-BlackItalic.ttf.gz
hass_frontend/fonts/roboto/Roboto-Bold.ttf
hass_frontend/fonts/roboto/Roboto-Bold.ttf.gz
hass_frontend/fonts/roboto/Roboto-BoldItalic.ttf
hass_frontend/fonts/roboto/Roboto-BoldItalic.ttf.gz
hass_frontend/fonts/roboto/Roboto-Italic.ttf
hass_frontend/fonts/roboto/Roboto-Italic.ttf.gz
hass_frontend/fonts/roboto/Roboto-Light.ttf
hass_frontend/fonts/roboto/Roboto-Light.ttf.gz
hass_frontend/fonts/roboto/Roboto-LightItalic.ttf
hass_frontend/fonts/roboto/Roboto-LightItalic.ttf.gz
hass_frontend/fonts/roboto/Roboto-Medium.ttf
hass_frontend/fonts/roboto/Roboto-Medium.ttf.gz
hass_frontend/fonts/roboto/Roboto-MediumItalic.ttf
hass_frontend/fonts/roboto/Roboto-MediumItalic.ttf.gz
hass_frontend/fonts/roboto/Roboto-Regular.ttf
hass_frontend/fonts/roboto/Roboto-Regular.ttf.gz
hass_frontend/fonts/roboto/Roboto-Thin.ttf
hass_frontend/fonts/roboto/Roboto-Thin.ttf.gz
hass_frontend/fonts/roboto/Roboto-ThinItalic.ttf
hassmart_home_assistant_frontend-20180310.0.dist-info/DESCRIPTION.rst
hassmart_home_assistant_frontend-20180310.0.dist-info/METADATA
hassmart_home_assistant_frontend-20180310.0.dist-info/RECORD
hassmart_home_assistant_frontend-20180310.0.dist-info/WHEEL
hassmart_home_assistant_frontend-20180310.0.dist-info/metadata.json
hassmart_home_assistant_frontend-20180310.0.dist-info/top_level.txt
