Metadata-Version: 2.0
Name: hassmart-home-assistant-frontend
Version: 20180310.0
Summary: The Hassmart frontend, powered by homeassistant
Home-page: https://github.com/home-assistant/home-assistant-polymer
Author: The Home Assistant Authors
Author-email: hello@home-assistant.io
License: Apache License 2.0
Platform: UNKNOWN
Requires-Dist: user-agents (==1.1.0)
